{"ai_enabled":true,"allow_pitlane_collisions":true,"allow_rolling_start":true,"allow_standing_start":true,"award_exempt":false,"category":"road","category_id":2,"closes":"2022-10-31","config_name":"Grand Prix","corners_per_lap":17,"created":"2016-01-05T11:23:38Z","first_sale":"2016-06-03T00:00:00Z","folder":"/img/tracks/autodromointernazionaleenzoedinoferrari","free_with_subscription":false,"fully_lit":false,"grid_stalls":62,"has_opt_path":false,"has_short_parade_lap":false,"has_start_zone":false,"has_svg_map":true,"is_dirt":false,"is_oval":false,"is_ps_purchasable":true,"lap_scoring":0,"latitude":44.3443574,"location":"Imola, Emilia-Romagna, Italy","longitude":11.717198,"max_cars":62,"night_lighting":false,"nominal_lap_time":112.23193,"number_pitstalls":37,"opens":"2022-02-01","package_id":197,"pit_road_speed_limit":50,"price":14.95,"price_display":"$14.95","priority":0,"purchasable":true,"qualify_laps":2,"rain_enabled":true,"restart_on_left":true,"retired":false,"search_filters":"road","site_url":"http://www.autodromoimola.com/index.php","sku":10403,"small_image":"autodromointernazionaleenzoedinoferrari-small.jpg","solo_laps":5,"start_on_left":true,"supports_grip_compound":false,"tech_track":false,"time_zone":"Europe/Rome","track_config_length":3.05,"track_dirpath":"imola\\gp","track_id":266,"track_name":"Autodromo Internazionale Enzo e Dino Ferrari","track_types":[{"track_type":"road"}]}