{"coordinates":"29.185169,-81.072722","detail_copy":"<p>No one could have known it then, but when Daytona International Speedway opened in 1959, it marked the beginning of a new era in American motorsport. As a replacement for the old beach road course a few miles east, the high-banked, 2.5-mile Florida tri-oval represented the leading edge of a wave of construction of big, paved speed palaces. Before Daytona, Indianapolis was the only American oval track longer than 1.25 miles, and most racing took place on dirt ovals a mile or less in length. From the very first Daytona 500, won by Lee Petty in a three-way photo finish, those high banks, so steep that it is hard to walk up them, proved a favorable venue for wide-open stock car racing, and Daytona kicked-off the growth of NASCAR as we know it today.</p><p>Daytona was also the first multi-use facility, with a 3.56-mile road circuit incorporating the infield and most of the oval. Host not only to the Daytona 500, but the Rolex 24 sports car enduro, Bike Week's Daytona 200, Daytona KartWeek between Christmas and New Years and a host of driving-school, club and other events, Daytona’s busy and diverse schedule confirms the track's motto, \"The World Center of Racing.\"</p><p>Daytona International Speedway's infrastructure has grown and changed to such a degree that it would be almost unrecognizable today to someone who hasn't seen it since the track opened. But one thing hasn't changed over the past six decades: No driver can consider his or her career complete without notching a victory at Daytona.","detail_techspecs_copy":null,"detail_video":null,"folder":"/img/tracks/daytonainternationalspeedway","gallery_images":"1,2,3","gallery_prefix":"daytonainternationalspeedway-gallery","large_image":"daytonainternationalspeedway-large.jpg","logo":"/img/logos/tracks/daytonainternationalspeedway-logo.png","north":"90deg","num_svg_images":9,"small_image":"daytonainternationalspeedway-small.jpg","track_id":381,"track_map":"https://members-assets.iracing.com/public/track-maps/tracks_daytona_2011/381-daytona-2011-roadnascar2020/","track_map_layers":{"background":"background.svg","inactive":"inactive.svg","active":"active.svg","pitroad":"pitroad.svg","start-finish":"start-finish.svg","turns":"turns.svg"}}