{"coordinates":"42.5969530,-83.6848170","detail_copy":"<p>Some say it is located deep in New York State's Adirondack Mountains. Others believe it is close enough to Germany's famous Nurburgring to hear race engines echoing through the Eifel forests. All we know is it's called Centripetal Circuit - and it's available to all iRacing members FREE.</p> <p>Without divulging too much, we can say that Centripetal Circuit is a perfectly flat, perfectly round, 200-meter skid pad with lane markers placed concentrically every 10 meters. And it is an invaluable tool both for driver training and for chassis tuning. Work on your car-control skills, or dial in your set up on a particular car - or just drive around in circles to see how long you can maintain a power slide! We guarantee that you won't have to worry about spy photographers or the prying eyes of the competition whenever you visit this hidden gem of automotive research.</p>","detail_techspecs_copy":null,"detail_video":null,"folder":"/img/tracks/centripetalcircuit","gallery_images":"1,2,3,4,5","gallery_prefix":"centripetalcircuit-gallery","large_image":"centripetalcircuit-large.jpg","logo":"/img/logos/tracks/centripetalcircuit-logo.png","north":"90deg","num_svg_images":5,"small_image":"centripetalcircuit-small.jpg","track_id":143,"track_map":"https://members-assets.iracing.com/public/track-maps/tracks_skidpad/143-skidpad/","track_map_layers":{"background":"background.svg","inactive":"inactive.svg","active":"active.svg","pitroad":"pitroad.svg","start-finish":"start-finish.svg","turns":"turns.svg"}}